{
    "1": {
        "HashTag_Tag": "#kfdf",
        "data": "21\/10\/2016",
        "Videos_VideoFile": "cas.com",
        "Imagems_Nome": "sdfsdf",
        "FaixaEtaria_To": "20",
        "TipoPublicidade_Nome": "asdd",
        "Videos_Descricao": "adada",
        "Videos_Extensao": "dasd",
        "Genero_Nome": "Masc",
        "Videos_Nome": "ddas",
        "Empresas_Nome": "sELE",
        "FaixaEtaria_Descricao": "sdffd",
        "Publicidade_Titulo": "asdad",
        "TipoPublicidade_Descricao": "asdad",
        "Imagems_Descricao": "sfdsdf",
        "Imagems_Extensao": "fdsf",
        "FaixaEtaria_Nome": "xkdk10",
        "Endereco_MoradaCompleta": "adadad",
        "Imagems_ImageFile": "lslsd.com",
        "Publicidade_DescricaoTexto": "asdd",
        "Publicidade_URL": "asdds",
        "Videos_Tamanho": 15,
        "FaixaEtaria_From": "10",
        "Empresa_Descricao": "adads",
        "Imagems_Tamanho": 10
    },
    "2": {
        "HashTag_Tag": "#kfdf",
        "data": "21\/10\/2016",
        "Videos_VideoFile": "https:\/\/www.youtube.com\/watch?v=TRgZngAsvdk",
        "Imagems_Nome": "sdfsdf",
        "FaixaEtaria_To": "30",
        "TipoPublicidade_Nome": "asdd",
        "Videos_Descricao": "adada",
        "Videos_Extensao": "dasd",
        "Genero_Nome": "Masc",
        "Videos_Nome": "ddas",
        "Empresas_Nome": "Cabo Verde Telecom",
        "FaixaEtaria_Descricao": "Jovem",
        "Publicidade_Titulo": "Internet 3G na sua mao",
        "TipoPublicidade_Descricao": "Anuncio diario",
        "Imagems_Descricao": "sfdsdf",
        "Imagems_Extensao": "fdsf",
        "FaixaEtaria_Nome": "Jovem",
        "Endereco_MoradaCompleta": "adadad",
        "Imagems_ImageFile": "http:\/\/192.168.160.104:8080\/WebServicesREST\/images\/bannerPublicitario\/cvmovel.jpg",
        "Publicidade_DescricaoTexto": "Use e abuse da internet de borla",
        "Publicidade_URL": "asdds",
        "Videos_Tamanho": 15,
        "FaixaEtaria_From": "18",
        "Empresa_Descricao": "adads",
        "Imagems_Tamanho": 10
    },
    "3": {
        "HashTag_Tag": "#kfdf",
        "data": "02\/11\/2016",
        "Videos_VideoFile": "https:\/\/www.youtube.com\/watch?v=TRgZngAsvdk",
        "Imagems_Nome": "sdfsdf",
        "FaixaEtaria_To": "100",
        "TipoPublicidade_Nome": "asdd",
        "Videos_Descricao": "adada",
        "Videos_Extensao": "dasd",
        "Genero_Nome": "Unis",
        "Videos_Nome": "ddas",
        "Empresas_Nome": "Banco Africano de Investimento",
        "FaixaEtaria_Descricao": "Todos",
        "Publicidade_Titulo": "Novo emprestimo Habitação ",
        "TipoPublicidade_Descricao": "Anuncio diario",
        "Imagems_Descricao": "sfdsdf",
        "Imagems_Extensao": "fdsf",
        "FaixaEtaria_Nome": "Todos",
        "Endereco_MoradaCompleta": "adadad",
        "Imagems_ImageFile": "http:\/\/192.168.160.104:8080\/WebServicesREST\/images\/bannerPublicitario\/bca.png",
        "Publicidade_DescricaoTexto": "Novo emprestimo Habitação  com 2% de Juros pegar ou largar",
        "Publicidade_URL": "asdds",
        "Videos_Tamanho": 15,
        "FaixaEtaria_From": "0",
        "Empresa_Descricao": "adads",
        "Imagems_Tamanho": 10
    },
    "4": {
        "HashTag_Tag": "#kfdf",
        "data": "02\/11\/2016",
        "Videos_VideoFile": "https:\/\/www.youtube.com\/watch?v=TRgZngAsvdk",
        "Imagems_Nome": "sdfsdf",
        "FaixaEtaria_To": "100",
        "TipoPublicidade_Nome": "asdd",
        "Videos_Descricao": "adada",
        "Videos_Extensao": "dasd",
        "Genero_Nome": "Unis",
        "Videos_Nome": "ddas",
        "Empresas_Nome": "Garantia Seguradora",
        "FaixaEtaria_Descricao": "Todos",
        "Publicidade_Titulo": "Seguro automovel vivo",
        "TipoPublicidade_Descricao": "Anuncio Simples",
        "Imagems_Descricao": "sfdsdf",
        "Imagems_Extensao": "fdsf",
        "FaixaEtaria_Nome": "Todos",
        "Endereco_MoradaCompleta": "adadad",
        "Imagems_ImageFile": "http:\/\/192.168.160.104:8080\/WebServicesREST\/images\/bannerPublicitario\/bca.png",
        "Publicidade_DescricaoTexto": "Seguro automovel vivo a sua medida e interesse",
        "Publicidade_URL": "asdds",
        "Videos_Tamanho": 15,
        "FaixaEtaria_From": "0",
        "Empresa_Descricao": "adads",
        "Imagems_Tamanho": 10
    },
    "5": {
        "HashTag_Tag": "#kfdf",
        "data": "02\/11\/2016",
        "Videos_VideoFile": "https:\/\/www.youtube.com\/watch?v=TRgZngAsvdk",
        "Imagems_Nome": "sdfsdf",
        "FaixaEtaria_To": "100",
        "TipoPublicidade_Nome": "asdd",
        "Videos_Descricao": "adada",
        "Videos_Extensao": "dasd",
        "Genero_Nome": "Masc",
        "Videos_Nome": "ddas",
        "Empresas_Nome": "Caixa Economica de Cabo Verde",
        "FaixaEtaria_Descricao": "Todos",
        "Publicidade_Titulo": "Novo emprestimo Habitação ",
        "TipoPublicidade_Descricao": "Anuncio Simples",
        "Imagems_Descricao": "sfdsdf",
        "Imagems_Extensao": "fdsf",
        "FaixaEtaria_Nome": "Todos",
        "Endereco_MoradaCompleta": "adadad",
        "Imagems_ImageFile": "http:\/\/192.168.160.104:8080\/WebServicesREST\/images\/bannerPublicitario\/bca.png",
        "Publicidade_DescricaoTexto": "Novo emprestimo Habitação  com 2% de Juros pegar ou largar",
        "Publicidade_URL": "asdds",
        "Videos_Tamanho": 15,
        "FaixaEtaria_From": "0",
        "Empresa_Descricao": "adads",
        "Imagems_Tamanho": 10
    },
    "6": {
        "HashTag_Tag": "#kfdf",
        "data": "02\/11\/2016",
        "Videos_VideoFile": "asdasdasdas",
        "Imagems_Nome": "sdfsdf",
        "FaixaEtaria_To": "100",
        "TipoPublicidade_Nome": "asdd",
        "Videos_Descricao": "adada",
        "Videos_Extensao": "dasd",
        "Genero_Nome": "Fema",
        "Videos_Nome": "ddas",
        "Empresas_Nome": "Promotora",
        "FaixaEtaria_Descricao": "Todos",
        "Publicidade_Titulo": "Festa",
        "TipoPublicidade_Descricao": "Anuncio Simples",
        "Imagems_Descricao": "sfdsdf",
        "Imagems_Extensao": "fdsf",
        "FaixaEtaria_Nome": "Todos",
        "Endereco_MoradaCompleta": "adadad",
        "Imagems_ImageFile": "http:\/\/192.168.160.104:8080\/WebServicesREST\/images\/bannerPublicitario\/duro.jpg",
        "Publicidade_DescricaoTexto": "Festa",
        "Publicidade_URL": "asdds",
        "Videos_Tamanho": 15,
        "FaixaEtaria_From": "0",
        "Empresa_Descricao": "adads",
        "Imagems_Tamanho": 10
    }
}